Workbook

Sheet Summary
A1: CHAMP Budget Impact Summary — Merit Increases vs. Unreplaced Departures
A2: High-level exercise for conversation with Jenna — assumptions may change
A4: Line Item | B4: Annual Amount
A5: Combined Merit Increase (required 2% + optional 1.5%) | B5: ='Merit Increase'!$C$7
A6: Loaded Cost of 4 Unreplaced Departures | B6: ='Departed Staff Impact'!$F$9
A7: NET CHANGE TO ANTICIPATED LOADED CHAMP COST | B7: =B5-B6
A9: Departures as multiple of merit cost: | B9: =B6/B5
A11: Bottom line:
A12: Even funding the full merit package, total anticipated loaded CHAMP cost is projected to come in well below original budget, since the four unreplaced departures' loaded cost is several times larger than the combined merit increase. There is substantial room to absorb both merit increases without exceeding the original CHAMP cost envelope.
A14: Caveats:
A15: - Simplified exercise: straight full-year salaries, no partial-year proration for actual departure timing.
A16: - All 4 departed staff modeled at 100% FEMA/Federal F&A rate rather than their actual historical grant mix.
A17: - Merit figure uses the more precise effort-weighted methodology from the 7/13 report (as-given); departure
A18: figure uses the simplified flat-rate methodology — the two are not computed on identical bases.
A19: - See Assumptions tab for full detail.

Sheet Assumptions
A1: CHAMP Merit Impact vs. Departures — Working Assumptions
A2: High-level exercise for Jenna conversation — criteria may change later
A3: Label | B3: Value | C3: Notes
A4: SURS Fringe Rate | B4: 0.451 | C4: Academic Professional / SURS-eligible staff
A5: F&A Rate (FEMA/Federal, MTDC) | B5: 0.317 | C5: Assumed for ALL staff in this exercise, per Glenn's 7/15 simplification
A6: Loaded Cost Multiplier | B6: =(1+B4)*(1+B5) | C6: (1 + Fringe) x (1 + F&A) — used throughout
A9: Scope Notes
A10: - Straight full-year salaries used (no per-project/effort proration) per Glenn's 7/15 instruction.
A11: - All CHAMP staff assumed on FEMA/Federal grants for F&A purposes (simplification for this exercise).
A12: - Merit increase figures (2% + optional 1.5%) are taken as-given from CHAMP_Merit_Impact_AllStaff_2026-07-13.pdf,
A13: which used effort-weighted, grant-specific loading (a more precise methodology than this sheet's departure calc).
A14: - Departed-staff loaded costs on this sheet use the simplified flat-rate method above, NOT the effort-weighted
A15: method from the 7/13 document. Treat as directionally reliable, not a formal budget reconciliation.
A16: - Departure dates and last-known annual salaries pulled from CHAMP-PM D1 production database, 2026-07-15.

Sheet Merit Increase
A1: Merit Increase Cost — per CHAMP_Merit_Impact_AllStaff_2026-07-13.pdf
A2: Effort-weighted, grant-specific loading (actual methodology from source doc — taken as-given here)
A4: Component | B4: Scope | C4: Annualized Loaded Cost
A5: Required 2% across-the-board | B5: All 26 active CHAMP staff | C5: 69382.32
A6: Optional 1.5% additional | B6: 10 named staff (Marni, Sarah, Matthew, Arpita, Brad, Sabin, Nazmul, Caitlin, Tanner, Lena) — grant-funded, no GRF offset | C6: 18691.79
A7: TOTAL COMBINED MERIT INCREASE | C7: =SUM(C5:C6)

Sheet Departed Staff Impact
A1: Departed Staff — Unreplaced Loaded Cost (last 12 months)
A2: Simplified: straight full-year salary, flat SURS fringe + FEMA F&A rate applied to all staff
A4: Employee | B4: Departure Date | C4: Annual Salary | D4: Fringe Amount | E4: MTDC (Salary+Fringe) | F4: Loaded Cost (incl. F&A)
A5: Diana Davisson | B5: 2026-04-30 | C5: 111151 | D5: =C5*Assumptions!$B$4 | E5: =C5+D5 | F5: =E5*(1+Assumptions!$B$5)
A6: Dawn Cosentino | B6: 2025-12-16 | C6: 90923.44 | D6: =C6*Assumptions!$B$4 | E6: =C6+D6 | F6: =E6*(1+Assumptions!$B$5)
A7: Love Kumar | B7: 2026-03-19 | C7: 72000 | D7: =C7*Assumptions!$B$4 | E7: =C7+D7 | F7: =E7*(1+Assumptions!$B$5)
A8: Mary Richardson | B8: 2026-04-30 | C8: 72114 | D8: =C8*Assumptions!$B$4 | E8: =C8+D8 | F8: =E8*(1+Assumptions!$B$5)
A9: TOTAL | C9: =SUM(C5:C8) | D9: =SUM(D5:D8) | E9: =SUM(E5:E8) | F9: =SUM(F5:F8)
